MANIFEST.in
README.rst
setup.py
cucco/__init__.py
cucco/batch.py
cucco/cli.py
cucco/config.py
cucco/cucco.py
cucco/errors.py
cucco/logging.py
cucco/regex.py
cucco.egg-info/PKG-INFO
cucco.egg-info/SOURCES.txt
cucco.egg-info/dependency_links.txt
cucco.egg-info/entry_points.txt
cucco.egg-info/top_level.txt
cucco/data/stop-af
cucco/data/stop-ar
cucco/data/stop-bg
cucco/data/stop-bn
cucco/data/stop-br
cucco/data/stop-ca
cucco/data/stop-cs
cucco/data/stop-da
cucco/data/stop-de
cucco/data/stop-el
cucco/data/stop-en
cucco/data/stop-eo
cucco/data/stop-es
cucco/data/stop-et
cucco/data/stop-eu
cucco/data/stop-fa
cucco/data/stop-fi
cucco/data/stop-fr
cucco/data/stop-ga
cucco/data/stop-gl
cucco/data/stop-ha
cucco/data/stop-he
cucco/data/stop-hi
cucco/data/stop-hr
cucco/data/stop-hu
cucco/data/stop-hy
cucco/data/stop-id
cucco/data/stop-it
cucco/data/stop-ja
cucco/data/stop-ko
cucco/data/stop-la
cucco/data/stop-lv
cucco/data/stop-mr
cucco/data/stop-nl
cucco/data/stop-no
cucco/data/stop-pl
cucco/data/stop-pt
cucco/data/stop-ro
cucco/data/stop-ru
cucco/data/stop-sk
cucco/data/stop-sl
cucco/data/stop-so
cucco/data/stop-st
cucco/data/stop-sv
cucco/data/stop-sw
cucco/data/stop-th
cucco/data/stop-tr
cucco/data/stop-yo
cucco/data/stop-zh
cucco/data/stop-zu