Metadata-Version: 1.1
Name: cucco
Version: 2.0.0
Summary: Python library for text normalization
Home-page: https://github.com/davidmogar/cucco
Author: David Moreno-Garcia
Author-email: david.mogar@gmail.com
License: MIT
Download-URL: https://github.com/davidmogar/cucco/tarball/2.0.0
Keywords: normalization,language,text,manipulation
Platform: UNKNOWN
Classifier: Development Status :: 5 - Production/Stable
Classifier: Topic :: Software Development :: Libraries
Classifier: Intended Audience :: Developers
Classifier: Intended Audience :: Education
Classifier: Intended Audience :: Information Technology
Classifier: License :: OSI Approved :: MIT License
Classifier: Programming Language :: Python
Classifier: Programming Language :: Python :: 3
